softadaptx/__init__.py
softadaptx/algorithms/__init__.py
softadaptx/algorithms/base.py
softadaptx/algorithms/loss_weighted_variant.py
softadaptx/algorithms/normalized_slopes_variant.py
softadaptx/algorithms/original_variant.py
softadaptx/constants/__init__.py
softadaptx/constants/finite_difference_constants.py
softadaptx/constants/stability_constants.py
softadaptx/utilities/__init__.py
softadaptx/utilities/finite_difference.py
softadaptx/utilities/logging.py
softadaptx-0.0.1.dist-info/LICENSE
softadaptx-0.0.1.dist-info/METADATA
softadaptx-0.0.1.dist-info/WHEEL
softadaptx-0.0.1.dist-info/RECORD
