Metadata-Version: 2.3
Name: softadaptx
Version: 0.0.1
Summary: SoftAdapt: Techniques for Adaptive Loss Weighting of Neural Networks with Multi-Part Loss Functions
License: MIT
Keywords: Physics-Informed Neural Networks,Balancing PINNs Loss,Adaptive-Weighting,Multi-Task-Neural-Networks Optimization,Gradient-Descent-Weighting,Machine Learning
Author: Gerald Cuder
Author-email: gerald.cuder@icloud.com
Requires-Python: >=3.10
Classifier: Development Status :: 4 - Beta
Classifier: Intended Audience :: Science/Research
Classifier: License :: OSI Approved :: MIT License
Classifier: Programming Language :: Python :: 3.10
Classifier: Topic :: Scientific/Engineering :: Artificial Intelligence
Requires-Dist: findiff
Requires-Dist: numpy (>=1.20.0)
Requires-Dist: tqdm (>=4.47.0)
Project-URL: Repository, https://github.com/gcuder/SoftAdaptX
